airports/__init__.py
airports/airport_analysis_client.py
airports/search_airport_client.py
flights/__init__.py
flights/flight_analysis_client.py
flights/flight_visualization_client.py
flights/search_flight_client.py
airport_management-0.0.5.dist-info/METADATA
airport_management-0.0.5.dist-info/WHEEL
airport_management-0.0.5.dist-info/top_level.txt
airport_management-0.0.5.dist-info/RECORD
