Metadata-Version: 2.1
Name: airport-management
Version: 0.0.5
Summary: Library to visualize and manage airports and flights.
Author: Behnaz Rezaeifar, Viktoria Tilevska
